{
    "AX": {
        "error": 0.0049238329199743245, 
        "filter_outliers_dict": {
            "filter_outliers": true, 
            "iterations": 1, 
            "std_devs": 2
        }, 
        "fit": "average", 
        "value": 0.06635214613310376
    }, 
    "CDD": {
        "error": 0.0005145568632632378, 
        "filter_outliers_dict": {
            "filter_outliers": true, 
            "iterations": 1, 
            "std_devs": 10
        }, 
        "fit": "average", 
        "value": 0.2206315821023493
    }, 
    "H1": {
        "error": 0.06465923779975481, 
        "filter_outliers_dict": {
            "filter_outliers": true, 
            "iterations": 1, 
            "std_devs": 2
        }, 
        "fit": "average", 
        "value": 67.76193378596365
    }, 
    "H2": {
        "error": 0.005656882699876671, 
        "filter_outliers_dict": {
            "filter_outliers": true, 
            "iterations": 1, 
            "std_devs": 2
        }, 
        "fit": "average", 
        "value": -0.1766452368796219
    }, 
    "L1": {
        "error": 0.0018875881615721146, 
        "filter_outliers_dict": {
            "filter_outliers": true, 
            "iterations": 1, 
            "std_devs": 2
        }, 
        "fit": "average", 
        "value": 0.02252558132915038
    }, 
    "L2": {
        "error": 0.0045880845916223, 
        "filter_outliers_dict": {
            "filter_outliers": true, 
            "iterations": 1, 
            "std_devs": 2
        }, 
        "fit": "average", 
        "value": 0.01391360905956083
    }
}