{
    "AX": {
        "error": 0.00504550409179411, 
        "filter_outliers_dict": {
            "filter_outliers": true, 
            "iterations": 1, 
            "std_devs": 2
        }, 
        "fit": "average", 
        "value": -0.05901707703941294
    }, 
    "CDD": {
        "error": 2.4785944205809896e-06, 
        "filter_outliers_dict": {
            "filter_outliers": true, 
            "iterations": 1, 
            "std_devs": 10
        }, 
        "fit": "average", 
        "value": 5.020881245312834e-06
    }, 
    "H1": {
        "error": 0.0037747689331793263, 
        "filter_outliers_dict": {
            "filter_outliers": true, 
            "iterations": 1, 
            "std_devs": 2
        }, 
        "fit": "average", 
        "value": 0.09535612043058118
    }, 
    "H2": {
        "error": 0.005002838794938793, 
        "filter_outliers_dict": {
            "filter_outliers": true, 
            "iterations": 1, 
            "std_devs": 2
        }, 
        "fit": "average", 
        "value": -0.18109040360762876
    }, 
    "L1": {
        "error": 0.0020869048694306808, 
        "filter_outliers_dict": {
            "filter_outliers": true, 
            "iterations": 1, 
            "std_devs": 2
        }, 
        "fit": "average", 
        "value": -0.034716688288549624
    }, 
    "L2": {
        "error": 0.004226687133642477, 
        "filter_outliers_dict": {
            "filter_outliers": true, 
            "iterations": 1, 
            "std_devs": 2
        }, 
        "fit": "average", 
        "value": -0.010816193107595334
    }
}