{
    "AX": {
        "error": 0.004298743170340403, 
        "filter_outliers_dict": {
            "filter_outliers": true, 
            "iterations": 1, 
            "std_devs": 2
        }, 
        "fit": "average", 
        "value": -0.08101813284315337
    }, 
    "CDD": {
        "error": 2.974179155145082e-06, 
        "filter_outliers_dict": {
            "filter_outliers": true, 
            "iterations": 1, 
            "std_devs": 10
        }, 
        "fit": "average", 
        "value": 7.443270560081851e-06
    }, 
    "H1": {
        "error": 0.010652414963893136, 
        "filter_outliers_dict": {
            "filter_outliers": true, 
            "iterations": 1, 
            "std_devs": 2
        }, 
        "fit": "average", 
        "value": -0.007100450796811634
    }, 
    "H2": {
        "error": 0.005208972991292716, 
        "filter_outliers_dict": {
            "filter_outliers": true, 
            "iterations": 1, 
            "std_devs": 2
        }, 
        "fit": "average", 
        "value": -0.20776544843476027
    }, 
    "L1": {
        "error": 0.0017823570846947142, 
        "filter_outliers_dict": {
            "filter_outliers": true, 
            "iterations": 1, 
            "std_devs": 2
        }, 
        "fit": "average", 
        "value": -0.03304329369545272
    }, 
    "L2": {
        "error": 0.004558929867426707, 
        "filter_outliers_dict": {
            "filter_outliers": true, 
            "iterations": 1, 
            "std_devs": 2
        }, 
        "fit": "average", 
        "value": -0.024423237549868183
    }
}