{
    "Ar36": {
        "error": 0.0008397376218328437, 
        "filter_outliers_dict": {
            "filter_outliers": true, 
            "iterations": 1, 
            "std_devs": 2
        }, 
        "fit": "Parabolic", 
        "value": 0.25357455735699636
    }, 
    "Ar37": {
        "error": 0.004995810481698951, 
        "filter_outliers_dict": {
            "filter_outliers": true, 
            "iterations": 1, 
            "std_devs": 2
        }, 
        "fit": "linear", 
        "value": 0.03048158129744577
    }, 
    "Ar38": {
        "error": 0.0021344593624023143, 
        "filter_outliers_dict": {
            "filter_outliers": true, 
            "iterations": 1, 
            "std_devs": 2
        }, 
        "fit": "linear", 
        "value": 0.025553223038720534
    }, 
    "Ar39": {
        "error": 0.008428212797105223, 
        "filter_outliers_dict": {
            "filter_outliers": true, 
            "iterations": 1, 
            "std_devs": 2
        }, 
        "fit": "Parabolic", 
        "value": -0.03351324230608649
    }, 
    "Ar40": {
        "error": 0.011717555838446431, 
        "filter_outliers_dict": {
            "filter_outliers": true, 
            "iterations": 1, 
            "std_devs": 2
        }, 
        "fit": "Parabolic", 
        "value": 74.52590570377814
    }, 
    "Ar41": {
        "error": 0.005476380615322932, 
        "filter_outliers_dict": {
            "filter_outliers": true, 
            "iterations": 1, 
            "std_devs": 2
        }, 
        "fit": "linear", 
        "value": -0.17200503868154532
    }
}