{
    "Ar36": {
        "error": 0.0009469364364526925, 
        "filter_outliers_dict": {
            "filter_outliers": true, 
            "iterations": 1, 
            "std_devs": 2
        }, 
        "fit": "Parabolic", 
        "value": 0.24264750794915374
    }, 
    "Ar37": {
        "error": 0.0053951023270208155, 
        "filter_outliers_dict": {
            "filter_outliers": true, 
            "iterations": 1, 
            "std_devs": 2
        }, 
        "fit": "linear", 
        "value": 0.024327739662480294
    }, 
    "Ar38": {
        "error": 0.0021439714560316523, 
        "filter_outliers_dict": {
            "filter_outliers": true, 
            "iterations": 1, 
            "std_devs": 2
        }, 
        "fit": "linear", 
        "value": 0.03350774441205995
    }, 
    "Ar39": {
        "error": 0.008751159742657763, 
        "filter_outliers_dict": {
            "filter_outliers": true, 
            "iterations": 1, 
            "std_devs": 2
        }, 
        "fit": "Parabolic", 
        "value": -0.022774623444845536
    }, 
    "Ar40": {
        "error": 0.011537616292712114, 
        "filter_outliers_dict": {
            "filter_outliers": true, 
            "iterations": 1, 
            "std_devs": 2
        }, 
        "fit": "Parabolic", 
        "value": 70.56882197951587
    }, 
    "Ar41": {
        "error": 0.0032598778818306133, 
        "filter_outliers_dict": {
            "filter_outliers": true, 
            "iterations": 1, 
            "std_devs": 2
        }, 
        "fit": "linear", 
        "value": -0.06650188869416154
    }
}