{
    "Ar36": {
        "error": 2.3920316661880526e-05, 
        "filter_outliers_dict": {
            "filter_outliers": true, 
            "iterations": 1, 
            "std_devs": 2
        }, 
        "fit": "Parabolic", 
        "value": 0.00024777120495704334
    }, 
    "Ar37": {
        "error": 0.00513508336807626, 
        "filter_outliers_dict": {
            "filter_outliers": true, 
            "iterations": 1, 
            "std_devs": 2
        }, 
        "fit": "linear", 
        "value": 0.043223146413733114
    }, 
    "Ar38": {
        "error": 0.002385488132493406, 
        "filter_outliers_dict": {
            "filter_outliers": true, 
            "iterations": 1, 
            "std_devs": 2
        }, 
        "fit": "linear", 
        "value": 0.016954102940529178
    }, 
    "Ar39": {
        "error": 0.008731393275019803, 
        "filter_outliers_dict": {
            "filter_outliers": true, 
            "iterations": 1, 
            "std_devs": 2
        }, 
        "fit": "Parabolic", 
        "value": -0.02828716206309177
    }, 
    "Ar40": {
        "error": 0.011561073190748491, 
        "filter_outliers_dict": {
            "filter_outliers": true, 
            "iterations": 1, 
            "std_devs": 2
        }, 
        "fit": "Parabolic", 
        "value": 70.55646738870408
    }, 
    "Ar41": {
        "error": 0.003523143603493443, 
        "filter_outliers_dict": {
            "filter_outliers": true, 
            "iterations": 1, 
            "std_devs": 2
        }, 
        "fit": "linear", 
        "value": -0.06548819768920253
    }
}