{
    "Ar36": {
        "error": 0.0001641041934203372, 
        "fit": "previous", 
        "references": [
            {
                "exclude": false, 
                "record_id": "ba-01-J-2432"
            }
        ], 
        "value": 0.0035410420071895644
    }, 
    "Ar37": {
        "error": 0.005111519316599471, 
        "fit": "previous", 
        "references": [
            {
                "exclude": false, 
                "record_id": "ba-01-J-2432"
            }
        ], 
        "value": 0.06496725951067012
    }, 
    "Ar38": {
        "error": 0.002140916468657703, 
        "fit": "previous", 
        "references": [
            {
                "exclude": false, 
                "record_id": "ba-01-J-2432"
            }
        ], 
        "value": 0.008951072009354848
    }, 
    "Ar39": {
        "error": 0.00919696014902436, 
        "fit": "previous", 
        "references": [
            {
                "exclude": false, 
                "record_id": "ba-01-J-2432"
            }
        ], 
        "value": 0.025159997686907118
    }, 
    "Ar40": {
        "error": 0.019716811467028868, 
        "fit": "previous", 
        "references": [
            {
                "exclude": false, 
                "record_id": "ba-01-J-2432"
            }
        ], 
        "value": 0.1645423449848683
    }, 
    "PM41": {
        "error": 0.0739285190559522, 
        "fit": "previous", 
        "references": [
            {
                "exclude": false, 
                "record_id": "ba-01-J-2432"
            }
        ], 
        "value": 0.031056161299966772
    }
}